{
	"cmake" : 
	{
		"generator" : 
		{
			"multiConfig" : false,
			"name" : "MinGW Makefiles"
		},
		"paths" : 
		{
			"cmake" : "C:/Users/trelo/AppData/Local/JetBrains/Toolbox/apps/CLion/ch-0/231.8109.222/bin/cmake/win/x64/bin/cmake.exe",
			"cpack" : "C:/Users/trelo/AppData/Local/JetBrains/Toolbox/apps/CLion/ch-0/231.8109.222/bin/cmake/win/x64/bin/cpack.exe",
			"ctest" : "C:/Users/trelo/AppData/Local/JetBrains/Toolbox/apps/CLion/ch-0/231.8109.222/bin/cmake/win/x64/bin/ctest.exe",
			"root" : "C:/Users/trelo/AppData/Local/JetBrains/Toolbox/apps/CLion/ch-0/231.8109.222/bin/cmake/win/x64/share/cmake-3.25"
		},
		"version" : 
		{
			"isDirty" : false,
			"major" : 3,
			"minor" : 25,
			"patch" : 2,
			"string" : "3.25.2",
			"suffix" : ""
		}
	},
	"objects" : 
	[
		{
			"jsonFile" : "codemodel-v2-b162ad8335c8ef818f9e.json",
			"kind" : "codemodel",
			"version" : 
			{
				"major" : 2,
				"minor" : 4
			}
		},
		{
			"jsonFile" : "cache-v2-da44e3f713bf7cddd39a.json",
			"kind" : "cache",
			"version" : 
			{
				"major" : 2,
				"minor" : 0
			}
		},
		{
			"jsonFile" : "cmakeFiles-v1-36ae7f08c720b696c6da.json",
			"kind" : "cmakeFiles",
			"version" : 
			{
				"major" : 1,
				"minor" : 0
			}
		},
		{
			"jsonFile" : "toolchains-v1-5cbc28ff3e1199f4ec01.json",
			"kind" : "toolchains",
			"version" : 
			{
				"major" : 1,
				"minor" : 0
			}
		}
	],
	"reply" : 
	{
		"cache-v2" : 
		{
			"jsonFile" : "cache-v2-da44e3f713bf7cddd39a.json",
			"kind" : "cache",
			"version" : 
			{
				"major" : 2,
				"minor" : 0
			}
		},
		"cmakeFiles-v1" : 
		{
			"jsonFile" : "cmakeFiles-v1-36ae7f08c720b696c6da.json",
			"kind" : "cmakeFiles",
			"version" : 
			{
				"major" : 1,
				"minor" : 0
			}
		},
		"codemodel-v2" : 
		{
			"jsonFile" : "codemodel-v2-b162ad8335c8ef818f9e.json",
			"kind" : "codemodel",
			"version" : 
			{
				"major" : 2,
				"minor" : 4
			}
		},
		"toolchains-v1" : 
		{
			"jsonFile" : "toolchains-v1-5cbc28ff3e1199f4ec01.json",
			"kind" : "toolchains",
			"version" : 
			{
				"major" : 1,
				"minor" : 0
			}
		}
	}
}
